segmatic/__init__.py
segmatic/automatic_mask_generator.py
segmatic/build_sam.py
segmatic/predictor.py
segmatic/modeling/__init__.py
segmatic/modeling/common.py
segmatic/modeling/image_encoder.py
segmatic/modeling/mask_decoder.py
segmatic/modeling/prompt_encoder.py
segmatic/modeling/sam.py
segmatic/modeling/transformer.py
segmatic/utils/__init__.py
segmatic/utils/amg.py
segmatic/utils/onnx.py
segmatic/utils/transforms.py
segmatic-1.0.dist-info/LICENSE
segmatic-1.0.dist-info/METADATA
segmatic-1.0.dist-info/WHEEL
segmatic-1.0.dist-info/top_level.txt
segmatic-1.0.dist-info/RECORD
